gridThings/__init__.py
gridThings/gridThings.py
gridThingz-1.0.0.dist-info/LICENSE
gridThingz-1.0.0.dist-info/METADATA
gridThingz-1.0.0.dist-info/WHEEL
gridThingz-1.0.0.dist-info/top_level.txt
gridThingz-1.0.0.dist-info/RECORD
