Metadata-Version: 2.1
Name: gridThingz
Version: 1.0.0
Summary: A small package made to modify the numpy 2d data structure systed for ease of use.
Home-page: https://github.com/Zachary99/gridThingZ/
Author: Zephyrrus
Author-email: zachary.ehle@gmail.com
License: UNKNOWN
Project-URL: Bug Tracker, https://github.com/Zachary99/gridThingZ/issues/
Project-URL: Wiki, https://github.com/Zachary99/gridThingZ/wiki/
Platform: UNKNOWN
Classifier: Programming Language :: Python :: 3
Classifier: License :: OSI Approved :: MIT License
Classifier: Operating System :: OS Independent
Requires-Python: >=3.9
License-File: LICENSE
